requirements_filter/__init__.py
requirements_filter/requirements_filter.py
tests/__init__.py
tests/test_requirements_filter.py
requirements_filter-0.0.0.dist-info/LICENSE
requirements_filter-0.0.0.dist-info/METADATA
requirements_filter-0.0.0.dist-info/WHEEL
requirements_filter-0.0.0.dist-info/entry_points.txt
requirements_filter-0.0.0.dist-info/top_level.txt
requirements_filter-0.0.0.dist-info/RECORD
