Metadata-Version: 2.1
Name: requirements-filter
Version: 0.0.0
Summary: Removes private packages with @ from requirements file
Home-page: https://github.com/mashi/requirements-filter
Author: mashi
Author-email: 59000162+mashi@users.noreply.github.com
License: UNKNOWN
Project-URL: Bug Tracker, https://github.com/mashi/requirements-filter/issues
Platform: UNKNOWN
Classifier: Programming Language :: Python :: 3
Classifier: License :: OSI Approved :: MIT License
Classifier: Operating System :: OS Independent
Requires-Python: >=3.8
Requires-Dist: click (~=7.1.2)
